{
  "type": "extradelight:oven",
  "consumeContainer": false,
  "container": {
    "item": "extradelight:sheet"
  },
  "cookingtime": 800,
  "experience": 1.0,
  "ingredients": [
    {
      "item": "extradelight:stiff_peaks"
    },
    {
      "item": "extradelight:stiff_peaks"
    },
    {
      "item": "extradelight:stiff_peaks"
    },
    {
      "tag": "extradelight:sweetener"
    },
    {
      "tag": "extradelight:sweetener"
    },
    {
      "tag": "forge:whipped_cream"
    },
    {
      "tag": "extradelight:processed/fruit"
    },
    {
      "tag": "extradelight:processed/fruit"
    }
  ],
  "result": {
    "item": "extradelight:pavlova_item"
  }
}