{
  "type": "forge:conditional",
  "recipes": [
    {
      "conditions": [
        {
          "type": "forge:false"
        }
      ],
      "recipe": {
        "type": "farmersdelight:cooking",
        "container": {
          "item": "minecraft:glass_bottle"
        },
        "cookingtime": 200,
        "experience": 1.0,
        "ingredients": [
          {
            "item": "minecraft:barrier"
          }
        ],
        "recipe_book_tab": "meals",
        "result": {
          "item": "farmersdelight:beef_stew"
        }
      }
    }
  ]
}